compare_datasets_pure_python/__init__.py
compare_datasets_pure_python/compare_datasets.py
compare_datasets_pure_python/numeric_comparisons.py
compare_datasets_pure_python/prepare.py
compare_datasets_pure_python/string_comparisons.py
compare_datasets_pure_python/structure.py
compare_datasets_pure_python/tests/cases.md
compare_datasets_pure_python-0.0.2.dist-info/LICENSE.txt
compare_datasets_pure_python-0.0.2.dist-info/WHEEL
compare_datasets_pure_python-0.0.2.dist-info/METADATA
compare_datasets_pure_python-0.0.2.dist-info/RECORD
